bootstrap/LICENSE
bootstrap/version.txt
bootstrap/css/bootstrap-grid.css
bootstrap/css/bootstrap-grid.css.map
bootstrap/css/bootstrap-grid.min.css
bootstrap/css/bootstrap-grid.min.css.map
bootstrap/css/bootstrap-grid.rtl.css
bootstrap/css/bootstrap-grid.rtl.css.map
bootstrap/css/bootstrap-grid.rtl.min.css
bootstrap/css/bootstrap-grid.rtl.min.css.map
bootstrap/css/bootstrap-reboot.css
bootstrap/css/bootstrap-reboot.css.map
bootstrap/css/bootstrap-reboot.min.css
bootstrap/css/bootstrap-reboot.min.css.map
bootstrap/css/bootstrap-reboot.rtl.css
bootstrap/css/bootstrap-reboot.rtl.css.map
bootstrap/css/bootstrap-reboot.rtl.min.css
bootstrap/css/bootstrap-reboot.rtl.min.css.map
bootstrap/css/bootstrap-utilities.css
bootstrap/css/bootstrap-utilities.css.map
bootstrap/css/bootstrap-utilities.min.css
bootstrap/css/bootstrap-utilities.min.css.map
bootstrap/css/bootstrap-utilities.rtl.css
bootstrap/css/bootstrap-utilities.rtl.css.map
bootstrap/css/bootstrap-utilities.rtl.min.css
bootstrap/css/bootstrap-utilities.rtl.min.css.map
bootstrap/css/bootstrap.css
bootstrap/css/bootstrap.css.map
bootstrap/css/bootstrap.min.css
bootstrap/css/bootstrap.min.css.map
bootstrap/css/bootstrap.rtl.css
bootstrap/css/bootstrap.rtl.css.map
bootstrap/css/bootstrap.rtl.min.css
bootstrap/css/bootstrap.rtl.min.css.map
bootstrap/js/bootstrap.bundle.js
bootstrap/js/bootstrap.bundle.js.map
bootstrap/js/bootstrap.bundle.min.js
bootstrap/js/bootstrap.bundle.min.js.map
bootstrap/js/bootstrap.esm.js
bootstrap/js/bootstrap.esm.js.map
bootstrap/js/bootstrap.esm.min.js
bootstrap/js/bootstrap.esm.min.js.map
bootstrap/js/bootstrap.js
bootstrap/js/bootstrap.js.map
bootstrap/js/bootstrap.min.js
bootstrap/js/bootstrap.min.js.map
bootstrap_wrapper/__init__.py
bootstrap_wrapper-5.3.8.post1.dist-info/licenses/LICENSE
bootstrap_wrapper-5.3.8.post1.dist-info/METADATA
bootstrap_wrapper-5.3.8.post1.dist-info/WHEEL
bootstrap_wrapper-5.3.8.post1.dist-info/top_level.txt
bootstrap_wrapper-5.3.8.post1.dist-info/RECORD
