Metadata-Version: 2.4
Name: bootstrap-wrapper
Version: 5.3.8.post1
Summary: A Python wrapper to distribute Bootstrap CSS/JS assets
Author-email: Maximilian Clemens <m.clemens@mailbox.org>
License: MIT
Project-URL: Homepage, https://github.com/MaximilianClemens/python-bootstrap
Project-URL: Repository, https://github.com/MaximilianClemens/python-bootstrap
Project-URL: Bug Tracker, https://github.com/MaximilianClemens/python-bootstrap/issues
Keywords: bootstrap,css,javascript,web,frontend
Classifier: Development Status :: 5 - Production/Stable
Classifier: Intended Audience :: Developers
Classifier: Programming Language :: Python :: 3
Classifier: Programming Language :: Python :: 3.7
Classifier: Programming Language :: Python :: 3.8
Classifier: Programming Language :: Python :: 3.9
Classifier: Programming Language :: Python :: 3.10
Classifier: Programming Language :: Python :: 3.11
Classifier: Programming Language :: Python :: 3.12
Classifier: Topic :: Internet :: WWW/HTTP
Classifier: Topic :: Software Development :: Libraries :: Python Modules
Requires-Python: >=3.7
License-File: LICENSE
Dynamic: license-file
